dash_marvinjs/DashMarvinJS.py
dash_marvinjs/__init__.py
dash_marvinjs/_imports_.py
dash_marvinjs/dash_marvinjs.min.js
dash_marvinjs/dash_marvinjs.min.js.map
dash_marvinjs/decorators.py
dash_marvinjs/metadata.json
dash_marvinjs/package-info.json
dash_marvinjs/services.py
dash_marvinjs-0.5.0.dist-info/LICENSE
dash_marvinjs-0.5.0.dist-info/METADATA
dash_marvinjs-0.5.0.dist-info/WHEEL
dash_marvinjs-0.5.0.dist-info/top_level.txt
dash_marvinjs-0.5.0.dist-info/RECORD
