Metadata-Version: 2.1
Name: dash-marvinjs
Version: 0.5.0
Summary: MarvinJS to Dash integration
Home-page: UNKNOWN
Author: Ramil Nugmanov <nougmanoff@protonmail.com>
License: GPLv3
Platform: UNKNOWN
License-File: LICENSE
